br2/__init__.py
br2/custom_activation.py
br2/custom_constraint.py
br2/environment.py
br2/free_custom_systems.py
br2/free_simulator.py
br2/post_processing.py
br2/surface_connection_parallel_rod_numba.py
br2/version.py
br2-0.1.0.dist-info/LICENSE
br2-0.1.0.dist-info/METADATA
br2-0.1.0.dist-info/WHEEL
br2-0.1.0.dist-info/RECORD
