Metadata-Version: 2.1
Name: br2
Version: 0.1.0
Summary: Cosserat Rod based FREE assembly simulator
License: MIT
Author: Seung Hyun Kim
Author-email: skim0119@gmail.com
Requires-Python: >=3.8,<3.11
Classifier: License :: OSI Approved :: MIT License
Classifier: Programming Language :: Python :: 3
Classifier: Programming Language :: Python :: 3.8
Classifier: Programming Language :: Python :: 3.9
Classifier: Programming Language :: Python :: 3.10
Requires-Dist: matplotlib (>=3.7.1,<4.0.0)
Requires-Dist: pyelastica (>=0.3.1)
Requires-Dist: tqdm (>=4.65.0,<5.0.0)
